{
  "unversionedId": "Getting-Started/managefiles",
  "id": "Getting-Started/managefiles",
  "title": "Managing Files",
  "description": "A file is your data that consists of all budgets, transactions, accounts, and everything else. You can create as many files as you want. This lets you create multiple budgets, isolate accounts, and more.",
  "source": "@site/docs/Getting-Started/managefiles.md",
  "sourceDirName": "Getting-Started",
  "slug": "/Getting-Started/managefiles",
  "permalink": "/docs/Getting-Started/managefiles",
  "draft": false,
  "editUrl": "https://github.com/actualbudget/docs/tree/main/docs/Getting-Started/managefiles.md",
  "tags": [],
  "version": "current",
  "frontMatter": {
    "title": "Managing Files"
  },
  "sidebar": "docs",
  "previous": {
    "title": "Syncing Across Devices",
    "permalink": "/docs/Getting-Started/sync"
  },
  "next": {
    "title": "Migration Overview",
    "permalink": "/docs/Getting-Started/migration/migration-intro"
  }
}