{
  "id": "b5d65e39-8f8f-443c-9b08-429a9dbe10ca",
  "prevId": "00000000-0000-0000-0000-000000000000",
  "version": "7",
  "dialect": "postgresql",
  "tables": {
    "public.banks": {
      "name": "banks",
      "schema": "",
      "columns": {
        "id": {
          "name": "id",
          "type": "varchar(36)",
          "primaryKey": true,
          "notNull": true
        },
        "name": {
          "name": "name",
          "type": "text",
          "primaryKey": false,
          "notNull": false
        },
        "bank_id": {
          "name": "bank_id",
          "type": "text",
          "primaryKey": false,
          "notNull": false
        },
        "tombstone": {
          "name": "tombstone",
          "type": "boolean",
          "primaryKey": false,
          "notNull": false,
          "default": false
        }
      },
      "indexes": {},
      "foreignKeys": {},
      "compositePrimaryKeys": {},
      "uniqueConstraints": {},
      "policies": {},
      "checkConstraints": {},
      "isRLSEnabled": false
    }
  },
  "enums": {},
  "schemas": {},
  "sequences": {},
  "roles": {},
  "policies": {},
  "views": {},
  "_meta": {
    "columns": {},
    "schemas": {},
    "tables": {}
  }
}